docs/conf.py
examples/plot_fetch_datasets.py
examples/plot_spatial_nulls.py
neuromaps/__init__.py
neuromaps/_version.py
neuromaps/caret.py
neuromaps/civet.py
neuromaps/images.py
neuromaps/parcellate.py
neuromaps/plotting.py
neuromaps/points.py
neuromaps/resampling.py
neuromaps/stats.py
neuromaps/transforms.py
neuromaps/utils.py
neuromaps/datasets/__init__.py
neuromaps/datasets/_osf.py
neuromaps/datasets/annotations.py
neuromaps/datasets/atlases.py
neuromaps/datasets/contributions.py
neuromaps/datasets/utils.py
neuromaps/datasets/data/osf.json
neuromaps/datasets/tests/__init__.py
neuromaps/datasets/tests/test__osf.py
neuromaps/datasets/tests/test_annotations.py
neuromaps/datasets/tests/test_atlases.py
neuromaps/datasets/tests/test_utils.py
neuromaps/nulls/__init__.py
neuromaps/nulls/burt.py
neuromaps/nulls/nulls.py
neuromaps/nulls/spins.py
neuromaps/nulls/tests/__init__.py
neuromaps/nulls/tests/test_burt.py
neuromaps/nulls/tests/test_nulls.py
neuromaps/nulls/tests/test_spins.py
neuromaps/tests/__init__.py
neuromaps/tests/conftest.py
neuromaps/tests/test_caret.py
neuromaps/tests/test_civet.py
neuromaps/tests/test_images.py
neuromaps/tests/test_parcellate.py
neuromaps/tests/test_plotting.py
neuromaps/tests/test_points.py
neuromaps/tests/test_resampling.py
neuromaps/tests/test_stats.py
neuromaps/tests/test_transforms.py
neuromaps/tests/test_utils.py
neuromaps-0.0.5.dist-info/LICENSE
neuromaps-0.0.5.dist-info/METADATA
neuromaps-0.0.5.dist-info/WHEEL
neuromaps-0.0.5.dist-info/top_level.txt
neuromaps-0.0.5.dist-info/RECORD
