Metadata-Version: 2.1
Name: neuromaps
Version: 0.0.5
Summary: A toolbox for projecting, resampling, and comparing brain maps
Author-email: Network Neuroscience Lab <neuromaps-aaaadd3nmllrgres4illspuqqm@netneurolab.slack.com>
Maintainer-email: Network Neuroscience Lab <neuromaps-aaaadd3nmllrgres4illspuqqm@netneurolab.slack.com>
License: Attribution-NonCommercial-ShareAlike 4.0 International
Project-URL: Homepage, https://github.com/netneurolab/neuromaps
Keywords: network neuroscience,brain maps,annotated connectomes
Classifier: Development Status :: 3 - Alpha
Classifier: Intended Audience :: Science/Research
Classifier: License :: OSI Approved :: BSD License
Classifier: Programming Language :: Python :: 3 :: Only
Requires-Python: >=3.8
License-File: LICENSE
Requires-Dist: numpy >=1.14.0
Requires-Dist: scipy >=0.17
Requires-Dist: matplotlib
Requires-Dist: scikit-learn
Requires-Dist: nibabel >=3.0.0
Requires-Dist: nilearn
Provides-Extra: doc
Requires-Dist: sphinx <7.0.0,>=2.0 ; extra == 'doc'
Requires-Dist: sphinx-rtd-theme ; extra == 'doc'
Requires-Dist: sphinx-gallery ; extra == 'doc'
Provides-Extra: nulls
Requires-Dist: brainsmash >=0.10.0 ; extra == 'nulls'
Requires-Dist: brainspace ; extra == 'nulls'
Provides-Extra: style
Requires-Dist: flake8 ; extra == 'style'
Requires-Dist: ruff ; extra == 'style'
Provides-Extra: test
Requires-Dist: netneurotools ; extra == 'test'
Requires-Dist: coverage ; extra == 'test'
Requires-Dist: pytest >=3.6 ; extra == 'test'
Requires-Dist: pytest-cov ; extra == 'test'
